[{"date": "2025/01/01", "bot1": -1090, "bot2": 0, "bot3": 0, "bot4": 0, "bot5": 0}, {"date": "2025/01/02", "bot1": -8289, "bot2": 0, "bot3": 0, "bot4": 0, "bot5": 0}, {"date": "2025/01/03", "bot1": 8166, "bot2": 0, "bot3": 0, "bot4": 0, "bot5": 0}, {"date": "2025/01/04", "bot1": 288, "bot2": 0, "bot3": 0, "bot4": 0, "bot5": 0}, {"date": "2025/01/05", "bot1": 4986, "bot2": 0, "bot3": 0, "bot4": 0, "bot5": 0}, {"date": "2025/01/06", "bot1": 4995, "bot2": 0, "bot3": 0, "bot4": 0, "bot5": 0}, {"date": "2025/01/07", "bot1": 6695, "bot2": 0, "bot3": 0, "bot4": 0, "bot5": 0}, {"date": "2025/01/08", "bot1": -21433, "bot2": 0, "bot3": 0, "bot4": 0, "bot5": 0}, {"date": "2025/01/09", "bot1": 11791, "bot2": 0, "bot3": 0, "bot4": 0, "bot5": 0}, {"date": "2025/01/10", "bot1": 45895, "bot2": 0, "bot3": 0, "bot4": 0, "bot5": 0}, {"date": "2025/01/11", "bot1": 18483, "bot2": 0, "bot3": 0, "bot4": 0, "bot5": 0}, {"date": "2025/01/12", "bot1": 2386, "bot2": 0, "bot3": 0, "bot4": 0, "bot5": 0}, {"date": "2025/01/13", "bot1": -44783, "bot2": 0, "bot3": 0, "bot4": 0, "bot5": 0}, {"date": "2025/01/14", "bot1": 34551, "bot2": 0, "bot3": 0, "bot4": 0, "bot5": 0}, {"date": "2025/01/15", "bot1": 550, "bot2": 0, "bot3": 0, "bot4": 0, "bot5": 0}, {"date": "2025/01/16", "bot1": 4908, "bot2": 0, "bot3": 0, "bot4": 0, "bot5": 0}, {"date": "2025/01/17", "bot1": 7502, "bot2": 0, "bot3": 0, "bot4": 0, "bot5": 0}, {"date": "2025/01/18", "bot1": 13409, "bot2": 0, "bot3": 0, "bot4": 0, "bot5": 0}, {"date": "2025/01/19", "bot1": 1609, "bot2": 0, "bot3": 0, "bot4": 0, "bot5": 0}, {"date": "2025/01/20", "bot1": -9588, "bot2": 0, "bot3": 0, "bot4": 0, "bot5": 0}, {"date": "2025/01/21", "bot1": 25466, "bot2": 0, "bot3": 0, "bot4": 0, "bot5": 0}, {"date": "2025/01/22", "bot1": -4222, "bot2": 0, "bot3": 0, "bot4": 0, "bot5": 0}, {"date": "2025/01/23", "bot1": -14645, "bot2": 0, "bot3": 0, "bot4": 0, "bot5": 0}, {"date": "2025/01/24", "bot1": 2462, "bot2": 0, "bot3": 0, "bot4": 0, "bot5": 0}, {"date": "2025/01/25", "bot1": -9287, "bot2": 0, "bot3": 0, "bot4": 0, "bot5": 0}, {"date": "2025/01/26", "bot1": 3031, "bot2": 0, "bot3": 0, "bot4": 0, "bot5": 0}, {"date": "2025/01/27", "bot1": 9241, "bot2": 0, "bot3": 0, "bot4": 0, "bot5": 0}, {"date": "2025/01/28", "bot1": 16775, "bot2": 0, "bot3": 0, "bot4": 0, "bot5": 0}, {"date": "2025/01/29", "bot1": 2976, "bot2": 0, "bot3": 0, "bot4": 0, "bot5": 0}, {"date": "2025/01/30", "bot1": -20904, "bot2": 0, "bot3": 0, "bot4": 0, "bot5": 0}, {"date": "2025/01/31", "bot1": -12161, "bot2": 0, "bot3": 0, "bot4": 0, "bot5": 0}, {"date": "2025/02/01", "bot1": 20043, "bot2": 0, "bot3": 0, "bot4": 0, "bot5": 0}, {"date": "2025/02/02", "bot1": -16538, "bot2": 0, "bot3": 0, "bot4": 0, "bot5": 0}, {"date": "2025/02/03", "bot1": 10069, "bot2": 0, "bot3": 0, "bot4": 0, "bot5": 0}, {"date": "2025/02/04", "bot1": 15922, "bot2": 0, "bot3": 0, "bot4": 0, "bot5": 0}, {"date": "2025/02/05", "bot1": 7683, "bot2": 0, "bot3": 0, "bot4": 0, "bot5": 0}, {"date": "2025/02/06", "bot1": 11336, "bot2": 0, "bot3": 0, "bot4": 0, "bot5": 0}, {"date": "2025/02/07", "bot1": -9872, "bot2": 0, "bot3": 0, "bot4": 0, "bot5": 0}, {"date": "2025/02/08", "bot1": 16595, "bot2": 0, "bot3": 0, "bot4": 0, "bot5": 0}, {"date": "2025/02/09", "bot1": -551, "bot2": 0, "bot3": 0, "bot4": 0, "bot5": 0}, {"date": "2025/02/10", "bot1": 13679, "bot2": 0, "bot3": 0, "bot4": 0, "bot5": 0}, {"date": "2025/02/11", "bot1": 13270, "bot2": 0, "bot3": 0, "bot4": 0, "bot5": 0}, {"date": "2025/02/12", "bot1": 2567, "bot2": 0, "bot3": 0, "bot4": 0, "bot5": 0}, {"date": "2025/02/13", "bot1": 42412, "bot2": 0, "bot3": 0, "bot4": 0, "bot5": 0}, {"date": "2025/02/14", "bot1": 24078, "bot2": 0, "bot3": 0, "bot4": 0, "bot5": 0}, {"date": "2025/02/15", "bot1": 15599, "bot2": 0, "bot3": 0, "bot4": 0, "bot5": 0}, {"date": "2025/02/16", "bot1": 1627, "bot2": 0, "bot3": 0, "bot4": 0, "bot5": 0}, {"date": "2025/02/17", "bot1": 14776, "bot2": 0, "bot3": 0, "bot4": 0, "bot5": 0}, {"date": "2025/02/18", "bot1": -16197, "bot2": 0, "bot3": 0, "bot4": 0, "bot5": 0}, {"date": "2025/02/19", "bot1": 13007, "bot2": 0, "bot3": 0, "bot4": 0, "bot5": 0}, {"date": "2025/02/20", "bot1": 4108, "bot2": 0, "bot3": 0, "bot4": 0, "bot5": 0}, {"date": "2025/02/21", "bot1": 8390, "bot2": 0, "bot3": 0, "bot4": 0, "bot5": 0}, {"date": "2025/02/22", "bot1": -6538, "bot2": 0, "bot3": 0, "bot4": 0, "bot5": 0}, {"date": "2025/02/23", "bot1": -9675, "bot2": 0, "bot3": 0, "bot4": 0, "bot5": 0}, {"date": "2025/02/24", "bot1": 1176, "bot2": 0, "bot3": 0, "bot4": 0, "bot5": 0}, {"date": "2025/02/25", "bot1": 102083, "bot2": 0, "bot3": 0, "bot4": 0, "bot5": 0}, {"date": "2025/02/26", "bot1": -28403, "bot2": 0, "bot3": 0, "bot4": 0, "bot5": 0}, {"date": "2025/02/27", "bot1": -15947, "bot2": 0, "bot3": 0, "bot4": 0, "bot5": 0}, {"date": "2025/02/28", "bot1": 20441, "bot2": 0, "bot3": 0, "bot4": 0, "bot5": 0}, {"date": "2025/03/01", "bot1": 16301, "bot2": 0, "bot3": 0, "bot4": -2389, "bot5": 2194}, {"date": "2025/03/02", "bot1": 358, "bot2": 0, "bot3": 0, "bot4": 348, "bot5": 2205}, {"date": "2025/03/03", "bot1": -4314, "bot2": 0, "bot3": 0, "bot4": -1024, "bot5": 22374}, {"date": "2025/03/04", "bot1": 44532, "bot2": 964, "bot3": 0, "bot4": -2187, "bot5": -25777}, {"date": "2025/03/05", "bot1": 35983, "bot2": 0, "bot3": 0, "bot4": 1644, "bot5": 9706}, {"date": "2025/03/06", "bot1": 281, "bot2": 0, "bot3": 278, "bot4": 476, "bot5": 5577}, {"date": "2025/03/07", "bot1": 44467, "bot2": 0, "bot3": 1646, "bot4": 5248, "bot5": 1179}, {"date": "2025/03/08", "bot1": 23341, "bot2": 0, "bot3": 18388, "bot4": 2062, "bot5": -14359}, {"date": "2025/03/09", "bot1": 11496, "bot2": 618, "bot3": 3388, "bot4": -189, "bot5": -9316}, {"date": "2025/03/10", "bot1": 23038, "bot2": 13878, "bot3": 2106, "bot4": 1097, "bot5": -16746}, {"date": "2025/03/11", "bot1": 8385, "bot2": 10457, "bot3": 3813, "bot4": -914, "bot5": -573}, {"date": "2025/03/12", "bot1": 36448, "bot2": 7606, "bot3": 4961, "bot4": -1397, "bot5": 8106}, {"date": "2025/03/13", "bot1": 56761, "bot2": 30279, "bot3": 46923, "bot4": 3453, "bot5": 3262}, {"date": "2025/03/14", "bot1": 38613, "bot2": 37548, "bot3": 29977, "bot4": 1667, "bot5": 5583}, {"date": "2025/03/15", "bot1": 6750, "bot2": 20571, "bot3": 7450, "bot4": 1086, "bot5": 5517}, {"date": "2025/03/16", "bot1": -34703, "bot2": -8359, "bot3": -22756, "bot4": -159, "bot5": -6309}, {"date": "2025/03/17", "bot1": 2083, "bot2": -8628, "bot3": 5979, "bot4": 308, "bot5": -1293}, {"date": "2025/03/18", "bot1": 2352, "bot2": -428, "bot3": -79, "bot4": 263, "bot5": -2963}, {"date": "2025/03/19", "bot1": -597, "bot2": 18569, "bot3": -19615, "bot4": -214, "bot5": 15063}, {"date": "2025/03/20", "bot1": -10168, "bot2": 19560, "bot3": 3335, "bot4": 1141, "bot5": -870}, {"date": "2025/03/21", "bot1": -32560, "bot2": 5764, "bot3": -10689, "bot4": 1375, "bot5": -7214}, {"date": "2025/03/22", "bot1": -16176, "bot2": -26143, "bot3": -6976, "bot4": 3546, "bot5": 1873}, {"date": "2025/03/23", "bot1": 7666, "bot2": 10151, "bot3": 2663, "bot4": 5150, "bot5": 3653}, {"date": "2025/03/24", "bot1": -37031, "bot2": -7249, "bot3": -4977, "bot4": 2684, "bot5": 13103}, {"date": "2025/03/25", "bot1": -8970, "bot2": 22799, "bot3": 9099, "bot4": 1239, "bot5": -258}, {"date": "2025/03/26", "bot1": 29522, "bot2": 7354, "bot3": -40978, "bot4": -16607, "bot5": -3945}, {"date": "2025/03/27", "bot1": -9345, "bot2": -13360, "bot3": 76156, "bot4": 30091, "bot5": 224}, {"date": "2025/03/28", "bot1": -3190, "bot2": 29416, "bot3": -2091, "bot4": -4038, "bot5": -15401}, {"date": "2025/03/29", "bot1": 3208, "bot2": -29185, "bot3": 14420, "bot4": -7066, "bot5": -6046}, {"date": "2025/03/30", "bot1": 4740, "bot2": 3428, "bot3": 1336, "bot4": 3005, "bot5": 19978}, {"date": "2025/03/31", "bot1": 10483, "bot2": 16253, "bot3": 13806, "bot4": 7613, "bot5": 1470, "合計": 49626}, {"date": "2025/04/01", "bot1": 3471, "bot2": 9217, "bot3": -3646, "bot4": 2707, "bot5": 0}, {"date": "2025/04/02", "bot1": 12868, "bot2": 20716, "bot3": 10074, "bot4": 1741, "bot5": 0}, {"date": "2025/04/03", "bot1": -116677, "bot2": 63650, "bot3": -75122, "bot4": -4644, "bot5": 0}, {"date": "2025/04/04", "bot1": 8461, "bot2": 17622, "bot3": 2112, "bot4": 10074, "bot5": 0}, {"date": "2025/04/05", "bot1": 36674, "bot2": 12770, "bot3": 26322, "bot4": 4622, "bot5": 0}, {"date": "2025/04/06", "bot1": 3508, "bot2": 5288, "bot3": 1100, "bot4": -3149, "bot5": 0}, {"date": "2025/04/07", "bot1": 7041, "bot2": 24028, "bot3": 49197, "bot4": -30839, "bot5": 0}, {"date": "2025/04/08", "bot1": 14607, "bot2": 21020, "bot3": 10374, "bot4": -1450, "bot5": 0}, {"date": "2025/04/09", "bot1": -40006, "bot2": 4101, "bot3": -8283, "bot4": 499, "bot5": 0}, {"date": "2025/04/10", "bot1": -19746, "bot2": -41162, "bot3": 42731, "bot4": 10766, "bot5": 0}, {"date": "2025/04/11", "bot1": 9898, "bot2": 5971, "bot3": 27692, "bot4": 694, "bot5": 180}, {"date": "2025/04/12", "bot1": 2170, "bot2": -36197, "bot3": 6949, "bot4": 8593, "bot5": -1110}, {"date": "2025/04/13", "bot1": 471, "bot2": -3617, "bot3": 8478, "bot4": 910, "bot5": 300}, {"date": "2025/04/14", "bot1": -1282, "bot2": 50523, "bot3": 36830, "bot4": 9365, "bot5": 412}, {"date": "2025/04/15", "bot1": -2676, "bot2": 16804, "bot3": 10532, "bot4": 7713, "bot5": 0}, {"date": "2025/04/16", "bot1": 4086, "bot2": 1625, "bot3": -5085, "bot4": -4059, "bot5": 582}, {"date": "2025/04/17", "bot1": -4346, "bot2": 49938, "bot3": 32072, "bot4": 13992, "bot5": 7780}, {"date": "2025/04/18", "bot1": -4277, "bot2": 38447, "bot3": 5939, "bot4": 5881, "bot5": 356}, {"date": "2025/04/19", "bot1": 11236, "bot2": 5087, "bot3": 9873, "bot4": -141, "bot5": 0}, {"date": "2025/04/20", "bot1": 16891, "bot2": -3450, "bot3": 36489, "bot4": -6043, "bot5": 0}, {"date": "2025/04/21", "bot1": 189, "bot2": 14673, "bot3": 22839, "bot4": 13998, "bot5": 0}, {"date": "2025/04/22", "bot1": 12376, "bot2": 55618, "bot3": 30601, "bot4": 3511, "bot5": 413}, {"date": "2025/04/23", "bot1": 2624, "bot2": -11547, "bot3": 32534, "bot4": 5661, "bot5": 198}, {"date": "2025/04/24", "bot1": 3012, "bot2": 4763, "bot3": -11480, "bot4": 12358, "bot5": 0}, {"date": "2025/04/25", "bot1": 14393, "bot2": 27634, "bot3": 66544, "bot4": 12241, "bot5": 0}, {"date": "2025/04/26", "bot1": -2939, "bot2": -242, "bot3": 18104, "bot4": -9491, "bot5": 4673}, {"date": "2025/04/27", "bot1": 1011, "bot2": 6608, "bot3": 52809, "bot4": 11617, "bot5": 0}, {"date": "2025/04/28", "bot1": -5282, "bot2": 74529, "bot3": 21116, "bot4": -6028, "bot5": -8012}, {"date": "2025/04/29", "bot1": 6172, "bot2": 45320, "bot3": 939, "bot4": 14542, "bot5": 0}, {"date": "2025/04/30", "bot1": 276, "bot2": 4751, "bot3": -4435, "bot4": 2401, "bot5": 0}, {"date": "2025/05/01", "bot1": -23640, "bot2": 76859, "bot3": -23113, "bot4": -14596, "bot5": 6}, {"date": "2025/05/02", "bot1": 4357, "bot2": 65058, "bot3": 33142, "bot4": 18932, "bot5": 427}, {"date": "2025/05/03", "bot1": 0, "bot2": 124, "bot3": 35294, "bot4": -8426, "bot5": 0}, {"date": "2025/05/04", "bot1": 18184, "bot2": 84158, "bot3": 7670, "bot4": 10296, "bot5": 0}, {"date": "2025/05/05", "bot1": 6131, "bot2": 10875, "bot3": 25096, "bot4": -20154, "bot5": 0}, {"date": "2025/05/06", "bot1": 0, "bot2": 62963, "bot3": 65399, "bot4": 12574, "bot5": -237}, {"date": "2025/05/07", "bot1": 3440, "bot2": 8486, "bot3": -26269, "bot4": 28297, "bot5": -139}, {"date": "2025/05/08", "bot1": 0, "bot2": -14595, "bot3": 1095, "bot4": 4174, "bot5": 2699}, {"date": "2025/05/09", "bot1": -3666, "bot2": -277272, "bot3": -15449, "bot4": 64522, "bot5": 6609}, {"date": "2025/05/10", "bot1": 5730, "bot2": 37776, "bot3": 115305, "bot4": 16954, "bot5": 309}, {"date": "2025/05/11", "bot1": -3476, "bot2": 71346, "bot3": 88182, "bot4": 22510, "bot5": 820}, {"date": "2025/05/12", "bot1": 6824, "bot2": 25582, "bot3": 208705, "bot4": 31816, "bot5": 4209}, {"date": "2025/05/13", "bot1": -18601, "bot2": 102532, "bot3": 71045, "bot4": 3358, "bot5": 1248}, {"date": "2025/05/14", "bot1": -3925, "bot2": 59290, "bot3": 38809, "bot4": -6692, "bot5": 334}, {"date": "2025/05/15", "bot1": 5028, "bot2": -30935, "bot3": -80109, "bot4": 3086, "bot5": 111}, {"date": "2025/05/16", "bot1": 3659, "bot2": 80995, "bot3": 18686, "bot4": 35433, "bot5": 448}, {"date": "2025/05/17", "bot1": 1764, "bot2": -61147, "bot3": 83629, "bot4": 10722, "bot5": 50}, {"date": "2025/05/18", "bot1": -168, "bot2": -37688, "bot3": 51764, "bot4": -9475, "bot5": -923}, {"date": "2025/05/19", "bot1": 1338, "bot2": -24331, "bot3": -32112, "bot4": 29530, "bot5": 1092}, {"date": "2025/05/20", "bot1": 8913, "bot2": 6599, "bot3": 37270, "bot4": 9313, "bot5": 279}, {"date": "2025/05/21", "bot1": 6997, "bot2": 25195, "bot3": 86253, "bot4": 14556, "bot5": 487}, {"date": "2025/05/22", "bot1": -9977, "bot2": 58609, "bot3": 69573, "bot4": 9112, "bot5": -822}, {"date": "2025/05/23", "bot1": -23180, "bot2": 130679, "bot3": -19575, "bot4": 68985, "bot5": 1628}, {"date": "2025/05/24", "bot1": 11483, "bot2": 49396, "bot3": -9789, "bot4": -23067, "bot5": 0}, {"date": "2025/05/25", "bot1": 19959, "bot2": -11498, "bot3": -66554, "bot4": 6267, "bot5": -56}, {"date": "2025/05/26", "bot1": 25936, "bot2": 19515, "bot3": 37453, "bot4": 101903, "bot5": -968}, {"date": "2025/05/27", "bot1": 23442, "bot2": 21326, "bot3": 120733, "bot4": 47410, "bot5": 3896}, {"date": "2025/05/28", "bot1": 15198, "bot2": -76785, "bot3": 5654, "bot4": -610, "bot5": -2604}, {"date": "2025/05/29", "bot1": 29556, "bot2": 6447, "bot3": 42980, "bot4": 106447, "bot5": 1091}, {"date": "2025/05/30", "bot1": 11284, "bot2": -157960, "bot3": 109054, "bot4": -9528, "bot5": 3877}, {"date": "2025/05/31", "bot1": 28015, "bot2": -93772, "bot3": -105567, "bot4": 52889, "bot5": 0}]